LICENSE.txt
MANIFEST.in
PyAudio-0.2.11-cp310-cp310-win32.whl
PyAudio-0.2.11-cp310-cp310-win_amd64.whl
PyAudio-0.2.11-cp38-cp38-win32.whl
PyAudio-0.2.11-cp38-cp38-win_amd64.whl
PyAudio-0.2.11-cp39-cp39-win32.whl
PyAudio-0.2.11-cp39-cp39-win_amd64.whl
PyAudio-0.2.13-cp311-cp311-win32.whl
PyAudio-0.2.13-cp311-cp311-win_amd64.whl
README.md
setup.cfg
setup.py
SpyWare/SpyWare.py
SpyWare/__init__.py
SpyWare/__main__.py
SpyWare.egg-info/PKG-INFO
SpyWare.egg-info/SOURCES.txt
SpyWare.egg-info/dependency_links.txt
SpyWare.egg-info/entry_points.txt
SpyWare.egg-info/requires.txt
SpyWare.egg-info/top_level.txt
SpyWare/AudioLogger/AudioLogger.py
SpyWare/AudioLogger/__init__.py
SpyWare/AudioLogger/__main__.py
SpyWare/AudioLogger/audioSpy.conf
SpyWare/ClipboardLogger/ClipboardLogger.py
SpyWare/ClipboardLogger/__init__.py
SpyWare/ClipboardLogger/__main__.py
SpyWare/ClipboardLogger/clipboardSpy.conf
SpyWare/DomainsLogger/DomainsLogger.py
SpyWare/DomainsLogger/__init__.py
SpyWare/DomainsLogger/__main__.py
SpyWare/DomainsLogger/domainsSpy.conf
SpyWare/FilesLogger/FilesLogger.py
SpyWare/FilesLogger/__init__.py
SpyWare/FilesLogger/__main__.py
SpyWare/FilesLogger/filesSpy.conf
SpyWare/KeyLogger/KeyLogger.py
SpyWare/KeyLogger/__init__.py
SpyWare/KeyLogger/__main__.py
SpyWare/KeyLogger/keySpy.conf
SpyWare/ScreenLogger/ScreenLogger.py
SpyWare/ScreenLogger/__init__.py
SpyWare/ScreenLogger/__main__.py
SpyWare/ScreenLogger/screenSpy.conf
SpyWare/WebcamLogger/WebcamLogger.py
SpyWare/WebcamLogger/__init__.py
SpyWare/WebcamLogger/__main__.py
SpyWare/WebcamLogger/webcamSpy.conf